kraken_extract_from_html/__init__.py
kraken_extract_from_html/flask_routes.py
kraken_extract_from_html/kraken_extract_from_html.py
kraken_extract_from_html/extractors/__init__.py
kraken_extract_from_html/extractors/extract_emails.py
kraken_extract_from_html/extractors/extract_feeds.py
kraken_extract_from_html/extractors/extract_images.py
kraken_extract_from_html/extractors/extract_ioc.py
kraken_extract_from_html/extractors/extract_links.py
kraken_extract_from_html/extractors/extract_schemas.py
kraken_extract_from_html/extractors/extract_src.py
kraken_extract_from_html/extractors/extract_tables.py
kraken_extract_from_html/extractors/extract_text.py
kraken_extract_from_html/extractors/extract_title.py
kraken_extract_from_html/extractors/extract_urls.py
kraken_extract_from_html-0.0.21.dist-info/METADATA
kraken_extract_from_html-0.0.21.dist-info/WHEEL
kraken_extract_from_html-0.0.21.dist-info/top_level.txt
kraken_extract_from_html-0.0.21.dist-info/RECORD
