Metadata-Version: 2.1
Name: kraken-extract-from-html
Version: 0.0.21
Summary: Kraken Extract From HTML
Home-page: https://github.com/tactik8/kraken_extract_from_html2
Author: Tactik8
Author-email: info@tactik8.com
License: MIT
Classifier: License :: OSI Approved :: MIT License
Classifier: Programming Language :: Python :: 3
Classifier: Programming Language :: Python :: 3.8
Requires-Dist: beautifulsoup4
Requires-Dist: extruct
Requires-Dist: html2text
Requires-Dist: ioc-finder
Requires-Dist: w3lib
Requires-Dist: boilerpy3
Requires-Dist: markdown
Requires-Dist: pandas
Requires-Dist: matplotlib
Requires-Dist: kraken-thing
